<Properties StartupConfiguration="{FCD76317-0B73-4E7A-9529-4E090614CF3D}|Default">
  <MonoDevelop.Ide.DebuggingService.Breakpoints>
    <BreakpointStore />
  </MonoDevelop.Ide.DebuggingService.Breakpoints>
  <MonoDevelop.Ide.Workspace ActiveConfiguration="Debug" />
  <MonoDevelop.Ide.DebuggingService.PinnedWatches />
  <MultiItemStartupConfigurations />
  <MonoDevelop.Ide.Workbench ActiveDocument="Example1/Program.cs">
    <Files>
      <File FileName="Example1/Program.cs" Line="22" Column="1" />
    </Files>
    <Pads>
      <Pad Id="ProjectPad">
        <State name="__root__">
          <Node name="Example1" expanded="True">
            <Node name="Example1" expanded="True">
              <Node name="Program.cs" selected="True" />
            </Node>
          </Node>
        </State>
      </Pad>
    </Pads>
  </MonoDevelop.Ide.Workbench>
  <MonoDevelop.Ide.ItemProperties.Example1 PreferredExecutionTarget="MonoDevelop.Default" />
</Properties>